[
  {
    "id": 1,
    "title": "Complete Web Development Bootcamp",
    "instructor": "John Doe",
    "duration": "20 hours",
    "rating": 4.1,
    "level": "Beginner",
    "description": "Learn full-stack web development from scratch.",
    "image": "https://i.ibb.co.com/0j7JXhcP/banner.avif",
    "category": "Development"
  },
  {
    "id": 2,
    "title": "React.js Mastery Course",
    "instructor": "Jane Smith",
    "duration": "15 hours",
    "rating": 4.2,
    "level": "Intermediate",
    "description": "Master React.js with real-world projects.",
    "image": "https://i.ibb.co.com/PsC4TFG7/photo-1498050108023-c5249f4df085.avif",
    "category": "Frontend"
  },
  {
    "id": 3,
    "title": "Next.js Full Course",
    "instructor": "Alex Johnson",
    "duration": "12 hours",
    "rating": 4.3,
    "level": "Intermediate",
    "description": "Learn server-side rendering and full-stack apps with Next.js.",
    "image": "https://i.ibb.co.com/YTQ04BTW/photo-1526948531399-320e7e40f0ca.avif",
    "category": "Frontend"
  },
  {
    "id": 4,
    "title": "UI/UX Design Fundamentals",
    "instructor": "Emily Davis",
    "duration": "10 hours",
    "rating": 4.4,
    "level": "Beginner",
    "description": "Learn modern UI/UX design principles and tools.",
    "image": "https://i.ibb.co.com/BHx412PH/photo-1584697964038-28e16a2b6a3a.avif",
    "category": "Design"
  },
  {
    "id": 5,
    "title": "Python for Beginners",
    "instructor": "Michael Brown",
    "duration": "18 hours",
    "rating": 4.5,
    "level": "Beginner",
    "description": "Start programming with Python from basics.",
    "image": "https://i.ibb.co.com/GN7YT8N/photo-1448932223592-d1fc686e76ea.avif",
    "category": "Programming"
  },
  {
    "id": 6,
    "title": "Data Structures & Algorithms",
    "instructor": "David Wilson",
    "duration": "25 hours",
    "rating": 4.6,
    "level": "Advanced",
    "description": "Master DSA for coding interviews and problem solving.",
    "image": "https://i.ibb.co.com/W9f8mVf/photo-1600880292203-757bb62b4baf.avif",
    "category": "Computer Science"
  }
]